streamlit_stl/.DS_Store
streamlit_stl/__init__.py
streamlit_stl/index.html
streamlit_stl/__pycache__/__init__.cpython-312.pyc
streamlit_stl/three_js_scripts/OrbitControls.js
streamlit_stl/three_js_scripts/STLLoader.js
streamlit_stl/three_js_scripts/stl-viewer.js
streamlit_stl/three_js_scripts/three.min.js
streamlit_stl-0.0.5.dist-info/LICENSE
streamlit_stl-0.0.5.dist-info/METADATA
streamlit_stl-0.0.5.dist-info/WHEEL
streamlit_stl-0.0.5.dist-info/top_level.txt
streamlit_stl-0.0.5.dist-info/RECORD
