Metadata-Version: 2.1
Name: streamlit_stl
Version: 0.0.5
Summary: A Streamlit component to display 3D models in STL format
Home-page: https://github.com/Lucandia/streamlit_stl
Author: Luca Monari
Author-email: Luca.Monari@mr.mpg.de
Requires-Python: >=3.7
License-File: LICENSE
